configs/__init__.py
configs/lrw_snv05x_tcn1x.json
labels/5WordsSortedList.txt
labels/__init__.py
lipreading/__init__.py
lipreading/dataloaders.py
lipreading/dataset.py
lipreading/mixup.py
lipreading/model.py
lipreading/optim_utils.py
lipreading/preprocess.py
lipreading/utils.py
lipreading/models/__init__.py
lipreading/models/attention.py
lipreading/models/resnet.py
lipreading/models/resnet1D.py
lipreading/models/shufflenetv2.py
lipreading/models/tcn.py
use_my_data/__init__.py
use_my_data/get_original_video.py
use_my_data/main.py
use_my_data/my_for_video.py
use_my_data/my_preprocess_video.py
RealtimeMouseDetect-1.2.dist-info/METADATA
RealtimeMouseDetect-1.2.dist-info/WHEEL
RealtimeMouseDetect-1.2.dist-info/license.txt
RealtimeMouseDetect-1.2.dist-info/top_level.txt
RealtimeMouseDetect-1.2.dist-info/RECORD
