Metadata-Version: 2.1
Name: RealtimeMouseDetect
Version: 1.2
Summary: A package to detect what you said without voice just by reading your lips in realtime
Home-page: UNKNOWN
Author: gyw
License: UNKNOWN
Platform: UNKNOWN
License-File: license.txt
